pyIPCMI.Parser.Files-1.1.3-py3.6-nspkg.pth
pyIPCMI/Parser/Files/CodeDOM.py
pyIPCMI/Parser/Files/__init__.py
pyIPCMI.Parser.Files-1.1.3.dist-info/LICENSE.md
pyIPCMI.Parser.Files-1.1.3.dist-info/METADATA
pyIPCMI.Parser.Files-1.1.3.dist-info/WHEEL
pyIPCMI.Parser.Files-1.1.3.dist-info/namespace_packages.txt
pyIPCMI.Parser.Files-1.1.3.dist-info/top_level.txt
pyIPCMI.Parser.Files-1.1.3.dist-info/RECORD
