Metadata-Version: 2.1
Name: pyIPCMI.Parser.Files
Version: 1.1.3
Summary: A parser for `*.files` files used in pyIPCMI.
Home-page: https://github.com/Paebbels/pyIPCMI.Parser.Files
Author: Patrick Lehmann
Author-email: Paebbels@gmail.com
License: UNKNOWN
Project-URL: Documentation, https://pyIPCMI.Parser.Files.readthedocs.io/en/latest/
Project-URL: Source Code, https://github.com/Paebbels/pyIPCMI.Parser.Files
Project-URL: Issue Tracker, https://github.com/Paebbels/pyIPCMI.Parser.Files/issues
Keywords: Python3 Parser pyIPCMI Code-DOM
Platform: UNKNOWN
Classifier: License :: OSI Approved :: Apache Software License
Classifier: Operating System :: OS Independent
Classifier: Programming Language :: Python :: 3 :: Only
Classifier: Programming Language :: Python :: 3.5
Classifier: Programming Language :: Python :: 3.6
Classifier: Programming Language :: Python :: 3.7
Classifier: Programming Language :: Python :: 3.8
Classifier: Development Status :: 5 - Production/Stable
Classifier: Intended Audience :: Developers
Classifier: Topic :: Utilities
Requires-Python: >=3.5
Requires-Dist: pyTokenizer
Requires-Dist: pyExploringCodeDOMParser
